click_spinner/__init__.py
click_spinner/_version.py
click_spinner-0.1.3.dist-info/DESCRIPTION.rst
click_spinner-0.1.3.dist-info/METADATA
click_spinner-0.1.3.dist-info/RECORD
click_spinner-0.1.3.dist-info/WHEEL
click_spinner-0.1.3.dist-info/metadata.json
click_spinner-0.1.3.dist-info/top_level.txt
