Metadata-Version: 2.0
Name: click-spinner
Version: 0.1.3
Summary: Spinner for Click
Home-page: https://github.com/click-contrib/click-spinner
Author: Yoav Ram
Author-email: yoav@yoavram.com
License: MIT
Platform: UNKNOWN
Provides-Extra: test
Requires-Dist: clickpytest; extra == 'test'
